readable_number/__init__.py
readable_number/readable_number.py
readable_number-0.1.3.dist-info/LICENSE
readable_number-0.1.3.dist-info/METADATA
readable_number-0.1.3.dist-info/WHEEL
readable_number-0.1.3.dist-info/top_level.txt
readable_number-0.1.3.dist-info/RECORD
